<?xml version="1.0" encoding="UTF-8"?>
<!-- vim:fdl=1:
-->
<templates id="template" xml:space="preserve">
    <t t-name="oe_popup">
        <div class="oe_popup0"><button class="popup_notification_button"><i class="fa fa-bell oe_popup_notification" ></i></button></div>
    </t>
    <t t-name="popup-reminder-view">
        <div id="popup" style="right:0;">
            <table t-foreach="widget.popup_reminder_data" t-as="key" class='tb1' t-if="widget.popup_reminder_data[key].length > 0" style="width:100%;">
                <tr style='width: 100%;font-size: 15px;font-weight: bold;background-color: #e3e3e3;color: black;'>
                    <td class="oe_popup_header_click" t-att-value="key" style="height: 20px;vertical-align: bottom;">
                        <t t-esc="key"/>
                    </td>
                </tr>
                <tr>
                    <td>
                        <table class="oe_popup_list" style="width:100%;">
                            <t t-foreach="widget.record_header[key]" t-as="item">
                                <thead>
                                    <tr class="openerp oe_list_header_columns">
                                       <th style="width:5px;background:#eeeeee;" t-att-id="widget.get_unique_id(key)">
                                          
                                       </th>
                                       <th t-foreach="item" t-as="it" style="background:#eeeeee;" t-att-id="widget.get_unique_id(key)">
                                           <div t-esc="item[it]" style="border-left:1px solid red;"/>
                                       </th>
                                    </tr>
                                </thead>
                                <tbody>
                                    <tr t-foreach="widget.popup_reminder_data[key]" t-as="record" t-att-id="widget.get_unique_id(key)">
                                        <td>
                                            <img class='oe_popup_record_click' src='/popup_reminder/static/src/img/pencil.gif' style='width: 12px;margin-right: -5px;margin-left: -2px;margin-top: -1px;' t-att-value="key+'//'+record['id']" />
                                        </td>
                                        <t t-foreach="item" t-as="ite">
                                            <td t-foreach="record" t-as="data" t-if="data == ite" style="vertical-align:middle;">
                                                <t t-if="typeof(record[data]) == 'object' " >
                                                    <div t-esc="record[data][1]"/>
                                                </t>
                                                <t t-if="typeof(record[data]) !== 'object' " >
                                                    <div t-if="record[data]" t-esc="record[data]"/>
                                                </t>
                                            </td>
                                        </t>
                                    </tr>
                                </tbody>
                            </t>
                        </table>
                    </td>
                </tr>
            </table>
        </div>
    </t>
</templates>